upsetter/__init__.py
upsetter/cli.py
upsetter-0.1.0a1.dist-info/LICENSE
upsetter-0.1.0a1.dist-info/METADATA
upsetter-0.1.0a1.dist-info/WHEEL
upsetter-0.1.0a1.dist-info/entry_points.txt
upsetter-0.1.0a1.dist-info/top_level.txt
upsetter-0.1.0a1.dist-info/RECORD
